rhyolite_open_commerce_sdk/__init__.py
rhyolite_open_commerce_sdk/client.py
rhyolite_open_commerce_sdk/models.py
rhyolite_open_commerce_sdk-0.0.2.dist-info/METADATA
rhyolite_open_commerce_sdk-0.0.2.dist-info/WHEEL
rhyolite_open_commerce_sdk-0.0.2.dist-info/top_level.txt
rhyolite_open_commerce_sdk-0.0.2.dist-info/RECORD
