Metadata-Version: 2.4
Name: rhyolite-open-commerce-sdk
Version: 0.0.2
Summary: A Python SDK for Rhyolite Open Commerce API.
Author-email: Code Chef <admin@rhyoliteprime.com>
Project-URL: Homepage, https://github.com/kayaddo3/open-commerce-python-sdk
Project-URL: Bug Tracker, https://github.com/kayaddo3/open-commerce-python-sdk/issues
Classifier: Programming Language :: Python :: 3
Classifier: License :: OSI Approved :: MIT License
Classifier: Operating System :: OS Independent
Requires-Python: >=3.8
Requires-Dist: requests>=2.20.0
Requires-Dist: pydantic>=2.0
